{
    "version": "https://jsonfeed.org/version/1",
    "title": "LZQ的博客 • All posts by \"hexo\" tag",
    "description": "",
    "home_page_url": "http://example.com",
    "items": [
        {
            "id": "http://example.com/2025/03/16/%E7%94%A8HEXO%E6%A1%86%E6%9E%B6%E6%90%AD%E5%BB%BA%E4%BA%86%E4%B8%80%E4%B8%AA%E5%8D%9A%E5%AE%A2/",
            "url": "http://example.com/2025/03/16/%E7%94%A8HEXO%E6%A1%86%E6%9E%B6%E6%90%AD%E5%BB%BA%E4%BA%86%E4%B8%80%E4%B8%AA%E5%8D%9A%E5%AE%A2/",
            "title": "用HEXO框架搭建了一个博客",
            "date_published": "2025-03-16T05:59:10.000Z",
            "content_html": "<h3 id=\"hexo博客\"><a class=\"markdownIt-Anchor\" href=\"#hexo博客\">#</a> HEXO 博客</h3>\n<p>今天用 HEXO 框架搭建了一个自己的博客</p>\n<p>后续准备买个轻量级云服务托管这个博客，毕竟 GitHub 托管访问太慢了 Q_Q</p>\n<p>顺便用图床分享一张喜欢的壁纸：</p>\n<img data-src=\"https://img.131213.xyz/api/cfile/AgACAgUAAx0Eflp52gACfs9n1DkxpwHyjL5Yqpap-9uxJMr7VAACbcMxG4CMqFarLm833njj4QEAAwIAA3cAAzYE\" alt=\"final-fantasy-15-lq.jpg\">\n",
            "tags": [
                "hexo"
            ]
        }
    ]
}